swimlane_connector_utilities/__init__.py
swimlane_connector_utilities/asset_debugger.py
swimlane_connector_utilities/utilities.py
swimlane_connector_utilities-1.1.0.dist-info/LICENSE
swimlane_connector_utilities-1.1.0.dist-info/METADATA
swimlane_connector_utilities-1.1.0.dist-info/WHEEL
swimlane_connector_utilities-1.1.0.dist-info/top_level.txt
swimlane_connector_utilities-1.1.0.dist-info/RECORD
