Metadata-Version: 2.1
Name: swimlane-connector-utilities
Version: 1.1.0
Summary: Functions to simplify Swimlane connector development.
Home-page: https://github.com/swimlane/swimlane-connector-utilities
Author: Swimlane
Author-email: info@swimlane.com
Project-URL: Bug Tracker, https://github.com/swimlane/swimlane-connector-utilities/issues
Classifier: Programming Language :: Python :: 3
Classifier: License :: OSI Approved :: MIT License
Classifier: Operating System :: OS Independent
Requires-Python: >=3.6
License-File: LICENSE
Requires-Dist: swimlane-connector-exceptions <2,>=1.0.1
Requires-Dist: datetime-parser <2
Requires-Dist: requests <3,>=2
